Metadata-Version: 1.0
Name: cfastproject
Version: 2020.8.4.5
Summary: More convenient to create fastapi project
Home-page: https://github.com/ChuXiaoYi/fastproject
Author: Xiaoyi Chu
Author-email: 895706056@qq.com
License: GNU General Public License v3.0
Platform: UNKNOWN
